matclustering/LICENSE
matclustering/README.md
matclustering/__init__.py
matclustering/core/AbstractTrajectoryClustering.py
matclustering/core/SimilarityClustering.py
matclustering/core/__init__.py
matclustering/methods/__init__.py
matclustering/methods/_lib/evaluation.py
matclustering/methods/_lib/helper.py
matclustering/methods/_lib/preprocess.py
matclustering/methods/_under_dev/FreqTKMeans.py
matclustering/methods/_under_dev/agglomerative/__init__.py
matclustering/methods/_under_dev/agglomerative/agglomerative.py
matclustering/methods/_under_dev/corals/__init__.py
matclustering/methods/_under_dev/corals/corals.py
matclustering/methods/_under_dev/dbscan/__init__.py
matclustering/methods/_under_dev/dbscan/dbscan.py
matclustering/methods/_under_dev/dhillon/__init__.py
matclustering/methods/_under_dev/dhillon/dhillon.py
matclustering/methods/_under_dev/kluger/__init__.py
matclustering/methods/_under_dev/kluger/kluger.py
matclustering/methods/_under_dev/mattree/__init__.py
matclustering/methods/_under_dev/mattree/mattree.py
matclustering/methods/_under_dev/ococlus/__init__.py
matclustering/methods/_under_dev/ococlus/function.py
matclustering/methods/_under_dev/ococlus/ococlus.py
matclustering/methods/_under_dev/panda/__init__.py
matclustering/methods/_under_dev/panda/panda.py
matclustering/methods/_under_dev/tracoclus/__init__.py
matclustering/methods/_under_dev/tracoclus/function.py
matclustering/methods/_under_dev/tracoclus/tracoclus.py
matclustering/methods/coclustering/OCoClus.py
matclustering/methods/coclustering/SSOCoClus.py
matclustering/methods/hierarchical/__init__.py
matclustering/methods/hierarchical/mattree/MATTree.py
matclustering/methods/hierarchical/mattree/algorithm/TreeNodeObject.py
matclustering/methods/hierarchical/mattree/algorithm/check_label.py
matclustering/methods/hierarchical/mattree/algorithm/dashtree.py
matclustering/methods/hierarchical/mattree/algorithm/graphic_tree.py
matclustering/methods/hierarchical/mattree/algorithm/set_level.py
mat_clustering-0.1rc1.dist-info/LICENSE
mat_clustering-0.1rc1.dist-info/METADATA
mat_clustering-0.1rc1.dist-info/WHEEL
mat_clustering-0.1rc1.dist-info/top_level.txt
mat_clustering-0.1rc1.dist-info/RECORD
