Metadata-Version: 2.1
Name: mat-clustering
Version: 0.1rc1
Summary: Clustering Methods for Multiple Aspect Trajectory Data Mining
Home-page: https://github.com/mat-analysis/mat-clustering
Author: Yuri Nassar
Author-email: Yuri Santos <yuri.nassar@gmail.com>
Maintainer-email: Tarlis Tortelli Portela <tarlis@tarlis.com.br>, Yuri Santos <yuri.nassar@gmail.com>
License: GPL Version 3 or superior (see LICENSE file)
Project-URL: Homepage, https://github.com/mat-analysis/mat-clustering
Project-URL: Repository, https://github.com/mat-analysis/mat-clustering
Project-URL: Documentation, https://mat-analysis.github.io/mat-tools/mat-clustering/index.html
Project-URL: Download, https://pypi.org/project/mat-clustering/#files
Project-URL: Bug Tracker, https://github.com/mat-analysis/mat-clustering/issues
Keywords: data-science,machine-learning,data-mining,trajectory,multiple-trajectory,clustering
Classifier: Intended Audience :: Science/Research
Classifier: Intended Audience :: Developers
Classifier: License :: OSI Approved :: GNU General Public License v3 or later (GPLv3+)
Classifier: Programming Language :: Python
Classifier: Topic :: Software Development
Classifier: Topic :: Scientific/Engineering
Classifier: Topic :: Scientific/Engineering :: Artificial Intelligence
Classifier: Topic :: Scientific/Engineering :: Information Analysis
Classifier: Operating System :: OS Independent
Classifier: Operating System :: Microsoft :: Windows
Classifier: Operating System :: POSIX
Classifier: Operating System :: Unix
Classifier: Operating System :: MacOS
Classifier: Programming Language :: Python :: 3.10
Requires-Python: <3.10
License-File: LICENSE
Requires-Dist: glob2==0.7
Requires-Dist: numpy
Requires-Dist: pandas==1.3.4
Requires-Dist: mat-data
Requires-Dist: mat-model
Provides-Extra: binder
Requires-Dist: jupyter; extra == "binder"
Provides-Extra: dev
Requires-Dist: pre-commit; extra == "dev"
Requires-Dist: pytest; extra == "dev"
Requires-Dist: pytest-cov; extra == "dev"
Requires-Dist: pytest-xdist; extra == "dev"
Requires-Dist: wheel; extra == "dev"
Provides-Extra: dl
Provides-Extra: docs
Requires-Dist: jupyter; extra == "docs"
Requires-Dist: numpydoc; extra == "docs"
